mix_tools_sdk/__init__.py
mix_tools_sdk/client.py
mix_tools_sdk-0.1.2.dist-info/LICENSE
mix_tools_sdk-0.1.2.dist-info/METADATA
mix_tools_sdk-0.1.2.dist-info/WHEEL
mix_tools_sdk-0.1.2.dist-info/RECORD
