Metadata-Version: 2.3
Name: mix-tools-sdk
Version: 0.1.2
Summary: SDK for Mix Tools API
License: MIT
Author: Ivan Iufriakov i@box.mix.tools
Requires-Python: >=3.12,<4.0
Classifier: License :: OSI Approved :: MIT License
Classifier: Programming Language :: Python :: 3
Classifier: Programming Language :: Python :: 3.12
Classifier: Programming Language :: Python :: 3.13
Requires-Dist: httpx (>=0.28.0,<0.29.0)
Requires-Dist: pydantic (>=2.0.0,<3.0.0)
